LICENSE
MANIFEST.in
README
setup.py
ics2task/__init__.py
ics2task/utils.py
ics2task.egg-info/PKG-INFO
ics2task.egg-info/SOURCES.txt
ics2task.egg-info/dependency_links.txt
ics2task.egg-info/entry_points.txt
ics2task.egg-info/requires.txt
ics2task.egg-info/top_level.txt