Metadata-Version: 1.1
Name: ics2task
Version: 0.0.3
Summary: An utility that converts ICS events into tasks in Taskwarrior
Home-page: https://github.com/Spredzy/ics2task
Author: Yanis Guenane
Author-email: yanis@guenane.org
License: Apache V2.0
Platform: UNKNOWN
Classifier: Environment :: Console
Classifier: Intended Audience :: Developers
Classifier: Intended Audience :: Information Technology
Classifier: License :: OSI Approved :: Apache Software License
Classifier: Operating System :: POSIX :: Linux
Classifier: Programming Language :: Python :: 2.7
Classifier: Programming Language :: Python :: 3.4
